ot_markov_distances/__init__.py
ot_markov_distances/discounted_wl.py
ot_markov_distances/misc.py
ot_markov_distances/sinkhorn.py
ot_markov_distances/utils.py
ot_markov_distances/wl.py
ot_markov_distances-1.0.4.dist-info/METADATA
ot_markov_distances-1.0.4.dist-info/WHEEL
ot_markov_distances-1.0.4.dist-info/RECORD
