Metadata-Version: 2.1
Name: ot-markov-distances
Version: 1.0.4
Summary: Differentiable distances for graphs and markov chains using optimal transport
License: CECILL-B
Author: Tristan BRUGÈRE
Author-email: 67050900+nephanth@users.noreply.github.com
Requires-Python: >=3.10,<4.0
Classifier: License :: CeCILL-B Free Software License Agreement (CECILL-B)
Classifier: Programming Language :: Python :: 3
Classifier: Programming Language :: Python :: 3.10
Classifier: Programming Language :: Python :: 3.11
Classifier: Programming Language :: Python :: 3.12
Requires-Dist: networkx (>=3.1,<4.0)
Requires-Dist: torch (>=2.0.0,<3.0.0)
